aws_rekognition_tool/__init__.py
aws_rekognition_tool/config.py
aws_rekognition_tool/exceptions.py
aws_rekognition_tool/rekognition.py
aws_rekognition_tool/s3_handler.py
aws_rekognition_tool-0.5.0.dist-info/licenses/LICENSE
aws_rekognition_tool-0.5.0.dist-info/METADATA
aws_rekognition_tool-0.5.0.dist-info/WHEEL
aws_rekognition_tool-0.5.0.dist-info/top_level.txt
aws_rekognition_tool-0.5.0.dist-info/RECORD
